Metadata-Version: 2.1
Name: appdefender
Version: 0.4.1
Summary: Extrinsec AppDefender: Real time serverless protection
Home-page: https://www.extrinsec.com
Author: Extrinsec LLC
Author-email: support@extrinsec.com
License: Other/Proprietary License
Platform: Linux
Classifier: Development Status :: 5 - Production/Stable
Classifier: Environment :: Web Environment
Classifier: Intended Audience :: Developers
Classifier: License :: Other/Proprietary License
Classifier: Operating System :: POSIX :: Linux
Classifier: Programming Language :: Python :: 3
Classifier: Programming Language :: Python :: 3.6
Classifier: Programming Language :: Python :: 3.7
Classifier: Programming Language :: Python :: 3.8
Classifier: Programming Language :: Python :: 3.9
Classifier: Programming Language :: Python :: 3.10
Requires-Python: >=3.6, <4
License-File: LICENSE.txt
